prayer_tool/Entities.py
prayer_tool/__init__.py
prayer_tool/day.py
prayer_tool/prayer.py
prayer_tool/prayer_times.py
prayer_tool/testit.py
prayer_tool/testloc.py
prayer_tool/voice_assist.py
prayer_tool-3.2.0.dist-info/LICENSE
prayer_tool-3.2.0.dist-info/METADATA
prayer_tool-3.2.0.dist-info/WHEEL
prayer_tool-3.2.0.dist-info/top_level.txt
prayer_tool-3.2.0.dist-info/RECORD
