Metadata-Version: 2.1
Name: prayer-tool
Version: 3.2.0
Summary: The prayer tool api is a complete api to get the prayer schedule in your city. Fast, updated and easy to use !
Home-page: https://github.com/Nabil-Lahssini/prayer_assistant
Author: Nabil Lahssini
Author-email: NabilLahssini@gmail.com
License: MIT
Platform: UNKNOWN
Classifier: License :: OSI Approved :: MIT License
Classifier: Programming Language :: Python :: 3
Classifier: Programming Language :: Python :: 3.7
Requires-Dist: gtts
Requires-Dist: googletrans (==3.1.0a0)
Requires-Dist: requests
Requires-Dist: multipledispatch
